tree_sitter_types/__init__.py
tree_sitter_types/cli/__init__.py
tree_sitter_types/generation/__init__.py
tree_sitter_types/generation/code_generator.py
tree_sitter_types/node_types/__init__.py
tree_sitter_types/parser/__init__.py
tree_sitter_types/parser/parser.py
tree_sitter_types/parser/parser_manager.py
tree_sitter_types-0.0.2.dist-info/METADATA
tree_sitter_types-0.0.2.dist-info/WHEEL
tree_sitter_types-0.0.2.dist-info/entry_points.txt
tree_sitter_types-0.0.2.dist-info/top_level.txt
tree_sitter_types-0.0.2.dist-info/RECORD
