Metadata-Version: 2.1
Name: tree-sitter-types
Version: 0.0.2
Summary: Generate typed Python bindings for tree-sitter parsers
Home-page: https://github.com/joranhonig/python-tree-sitter-types
Author: Joran Honig
Author-email: joran.honig@gmail.com
Classifier: Programming Language :: Python :: 3
Classifier: Programming Language :: Python :: 3.7
Requires-Dist: click
Requires-Dist: tree-sitter
Requires-Dist: inflection
Requires-Dist: astor
Requires-Dist: GitPython
Requires-Dist: pydantic
Requires-Dist: black
Requires-Dist: toolz
